[1,["b0h/RfIu5ANYfScxzOlgRv@6c48a"],["_textureSource"],["cc.SpriteFrame","cc.SpriteAtlas"],0,[[[{"name":"death","spriteFrames":["death (29)","0clAvi2eJM5KXhi7xJuOgB@f4368","death (30)","0clAvi2eJM5KXhi7xJuOgB@e44d5","death (31)","0clAvi2eJM5KXhi7xJuOgB@14a6d","death (32)","0clAvi2eJM5KXhi7xJuOgB@d3c9a","death (33)","0clAvi2eJM5KXhi7xJuOgB@b0b8a","death (34)","0clAvi2eJM5KXhi7xJuOgB@8d6d5","death (35)","0clAvi2eJM5KXhi7xJuOgB@db90d","death (36)","0clAvi2eJM5KXhi7xJuOgB@063c3","death (37)","0clAvi2eJM5KXhi7xJuOgB@2b021","death (38)","0clAvi2eJM5KXhi7xJuOgB@44ca4","death (39)","0clAvi2eJM5KXhi7xJuOgB@b1b17","death (40)","0clAvi2eJM5KXhi7xJuOgB@80ae9","death (41)","0clAvi2eJM5KXhi7xJuOgB@4d12e","death (42)","0clAvi2eJM5KXhi7xJuOgB@c74c0"]}],[1],0,[],[],[]],[[{"name":"death (36)","rect":{"x":320,"y":640,"width":320,"height":320},"offset":{"x":0,"y":0},"originalSize":{"width":320,"height":320},"rotated":false,"capInsets":[0,0,0,0],"vertices":{"rawPosition":[],"indexes":[],"uv":[],"nuv":[],"minPos":{"x":0,"y":0,"z":0},"maxPos":{"x":0,"y":0,"z":0}},"packable":true,"pixelsToUnit":100,"pivot":{"x":0.5,"y":0.5},"meshType":0}],[0],0,[0],[0],[0]],[[{"name":"death (31)","rect":{"x":640,"y":0,"width":320,"height":320},"offset":{"x":0,"y":0},"originalSize":{"width":320,"height":320},"rotated":false,"capInsets":[0,0,0,0],"vertices":{"rawPosition":[],"indexes":[],"uv":[],"nuv":[],"minPos":{"x":0,"y":0,"z":0},"maxPos":{"x":0,"y":0,"z":0}},"packable":true,"pixelsToUnit":100,"pivot":{"x":0.5,"y":0.5},"meshType":0}],[0],0,[0],[0],[0]],[[{"name":"death (37)","rect":{"x":640,"y":640,"width":320,"height":320},"offset":{"x":0,"y":0},"originalSize":{"width":320,"height":320},"rotated":false,"capInsets":[0,0,0,0],"vertices":{"rawPosition":[],"indexes":[],"uv":[],"nuv":[],"minPos":{"x":0,"y":0,"z":0},"maxPos":{"x":0,"y":0,"z":0}},"packable":true,"pixelsToUnit":100,"pivot":{"x":0.5,"y":0.5},"meshType":0}],[0],0,[0],[0],[0]],[[{"name":"death (38)","rect":{"x":0,"y":960,"width":320,"height":320},"offset":{"x":0,"y":0},"originalSize":{"width":320,"height":320},"rotated":false,"capInsets":[0,0,0,0],"vertices":{"rawPosition":[],"indexes":[],"uv":[],"nuv":[],"minPos":{"x":0,"y":0,"z":0},"maxPos":{"x":0,"y":0,"z":0}},"packable":true,"pixelsToUnit":100,"pivot":{"x":0.5,"y":0.5},"meshType":0}],[0],0,[0],[0],[0]],[[{"name":"death (41)","rect":{"x":0,"y":1280,"width":320,"height":320},"offset":{"x":0,"y":0},"originalSize":{"width":320,"height":320},"rotated":false,"capInsets":[0,0,0,0],"vertices":{"rawPosition":[],"indexes":[],"uv":[],"nuv":[],"minPos":{"x":0,"y":0,"z":0},"maxPos":{"x":0,"y":0,"z":0}},"packable":true,"pixelsToUnit":100,"pivot":{"x":0.5,"y":0.5},"meshType":0}],[0],0,[0],[0],[0]],[[{"name":"death (40)","rect":{"x":640,"y":960,"width":320,"height":320},"offset":{"x":0,"y":0},"originalSize":{"width":320,"height":320},"rotated":false,"capInsets":[0,0,0,0],"vertices":{"rawPosition":[],"indexes":[],"uv":[],"nuv":[],"minPos":{"x":0,"y":0,"z":0},"maxPos":{"x":0,"y":0,"z":0}},"packable":true,"pixelsToUnit":100,"pivot":{"x":0.5,"y":0.5},"meshType":0}],[0],0,[0],[0],[0]],[[{"name":"death (34)","rect":{"x":640,"y":320,"width":320,"height":320},"offset":{"x":0,"y":0},"originalSize":{"width":320,"height":320},"rotated":false,"capInsets":[0,0,0,0],"vertices":{"rawPosition":[],"indexes":[],"uv":[],"nuv":[],"minPos":{"x":0,"y":0,"z":0},"maxPos":{"x":0,"y":0,"z":0}},"packable":true,"pixelsToUnit":100,"pivot":{"x":0.5,"y":0.5},"meshType":0}],[0],0,[0],[0],[0]],[[{"name":"death (33)","rect":{"x":320,"y":320,"width":320,"height":320},"offset":{"x":0,"y":0},"originalSize":{"width":320,"height":320},"rotated":false,"capInsets":[0,0,0,0],"vertices":{"rawPosition":[],"indexes":[],"uv":[],"nuv":[],"minPos":{"x":0,"y":0,"z":0},"maxPos":{"x":0,"y":0,"z":0}},"packable":true,"pixelsToUnit":100,"pivot":{"x":0.5,"y":0.5},"meshType":0}],[0],0,[0],[0],[0]],[[{"name":"death (39)","rect":{"x":320,"y":960,"width":320,"height":320},"offset":{"x":0,"y":0},"originalSize":{"width":320,"height":320},"rotated":false,"capInsets":[0,0,0,0],"vertices":{"rawPosition":[],"indexes":[],"uv":[],"nuv":[],"minPos":{"x":0,"y":0,"z":0},"maxPos":{"x":0,"y":0,"z":0}},"packable":true,"pixelsToUnit":100,"pivot":{"x":0.5,"y":0.5},"meshType":0}],[0],0,[0],[0],[0]],[[{"name":"death (42)","rect":{"x":320,"y":1280,"width":320,"height":320},"offset":{"x":0,"y":0},"originalSize":{"width":320,"height":320},"rotated":false,"capInsets":[0,0,0,0],"vertices":{"rawPosition":[],"indexes":[],"uv":[],"nuv":[],"minPos":{"x":0,"y":0,"z":0},"maxPos":{"x":0,"y":0,"z":0}},"packable":true,"pixelsToUnit":100,"pivot":{"x":0.5,"y":0.5},"meshType":0}],[0],0,[0],[0],[0]],[[{"name":"death (32)","rect":{"x":0,"y":320,"width":320,"height":320},"offset":{"x":0,"y":0},"originalSize":{"width":320,"height":320},"rotated":false,"capInsets":[0,0,0,0],"vertices":{"rawPosition":[],"indexes":[],"uv":[],"nuv":[],"minPos":{"x":0,"y":0,"z":0},"maxPos":{"x":0,"y":0,"z":0}},"packable":true,"pixelsToUnit":100,"pivot":{"x":0.5,"y":0.5},"meshType":0}],[0],0,[0],[0],[0]],[[{"name":"death (35)","rect":{"x":0,"y":640,"width":320,"height":320},"offset":{"x":0,"y":0},"originalSize":{"width":320,"height":320},"rotated":false,"capInsets":[0,0,0,0],"vertices":{"rawPosition":[],"indexes":[],"uv":[],"nuv":[],"minPos":{"x":0,"y":0,"z":0},"maxPos":{"x":0,"y":0,"z":0}},"packable":true,"pixelsToUnit":100,"pivot":{"x":0.5,"y":0.5},"meshType":0}],[0],0,[0],[0],[0]],[[{"name":"death (30)","rect":{"x":320,"y":0,"width":320,"height":320},"offset":{"x":0,"y":0},"originalSize":{"width":320,"height":320},"rotated":false,"capInsets":[0,0,0,0],"vertices":{"rawPosition":[],"indexes":[],"uv":[],"nuv":[],"minPos":{"x":0,"y":0,"z":0},"maxPos":{"x":0,"y":0,"z":0}},"packable":true,"pixelsToUnit":100,"pivot":{"x":0.5,"y":0.5},"meshType":0}],[0],0,[0],[0],[0]],[[{"name":"death (29)","rect":{"x":0,"y":0,"width":320,"height":320},"offset":{"x":0,"y":0},"originalSize":{"width":320,"height":320},"rotated":false,"capInsets":[0,0,0,0],"vertices":{"rawPosition":[],"indexes":[],"uv":[],"nuv":[],"minPos":{"x":0,"y":0,"z":0},"maxPos":{"x":0,"y":0,"z":0}},"packable":true,"pixelsToUnit":100,"pivot":{"x":0.5,"y":0.5},"meshType":0}],[0],0,[0],[0],[0]]]]
