[1,["b9fx3SHeFJSqAVNi32jbTp@6c48a"],["_textureSource"],["cc.SpriteFrame","cc.SpriteAtlas"],0,[[[{"name":"blockfront","spriteFrames":["blockface (1)","e9Rj+UnPdIr4tf43t8cE+X@fe070","blockface (2)","e9Rj+UnPdIr4tf43t8cE+X@4a269","blockface (3)","e9Rj+UnPdIr4tf43t8cE+X@25414","blockface (4)","e9Rj+UnPdIr4tf43t8cE+X@b81e2"]}],[1],0,[],[],[]],[[{"name":"blockface (3)","rect":{"x":640,"y":0,"width":320,"height":320},"offset":{"x":0,"y":0},"originalSize":{"width":320,"height":320},"rotated":false,"capInsets":[0,0,0,0],"vertices":{"rawPosition":[],"indexes":[],"uv":[],"nuv":[],"minPos":{"x":0,"y":0,"z":0},"maxPos":{"x":0,"y":0,"z":0}},"packable":true,"pixelsToUnit":100,"pivot":{"x":0.5,"y":0.5},"meshType":0}],[0],0,[0],[0],[0]],[[{"name":"blockface (2)","rect":{"x":320,"y":0,"width":320,"height":320},"offset":{"x":0,"y":0},"originalSize":{"width":320,"height":320},"rotated":false,"capInsets":[0,0,0,0],"vertices":{"rawPosition":[],"indexes":[],"uv":[],"nuv":[],"minPos":{"x":0,"y":0,"z":0},"maxPos":{"x":0,"y":0,"z":0}},"packable":true,"pixelsToUnit":100,"pivot":{"x":0.5,"y":0.5},"meshType":0}],[0],0,[0],[0],[0]],[[{"name":"blockface (4)","rect":{"x":960,"y":0,"width":320,"height":320},"offset":{"x":0,"y":0},"originalSize":{"width":320,"height":320},"rotated":false,"capInsets":[0,0,0,0],"vertices":{"rawPosition":[],"indexes":[],"uv":[],"nuv":[],"minPos":{"x":0,"y":0,"z":0},"maxPos":{"x":0,"y":0,"z":0}},"packable":true,"pixelsToUnit":100,"pivot":{"x":0.5,"y":0.5},"meshType":0}],[0],0,[0],[0],[0]],[[{"name":"blockface (1)","rect":{"x":0,"y":0,"width":320,"height":320},"offset":{"x":0,"y":0},"originalSize":{"width":320,"height":320},"rotated":false,"capInsets":[0,0,0,0],"vertices":{"rawPosition":[],"indexes":[],"uv":[],"nuv":[],"minPos":{"x":0,"y":0,"z":0},"maxPos":{"x":0,"y":0,"z":0}},"packable":true,"pixelsToUnit":100,"pivot":{"x":0.5,"y":0.5},"meshType":0}],[0],0,[0],[0],[0]]]]
